ncert_book_downloader-1.0.0.dist-info/licenses/LICENSE
ncert_downloader/__init__.py
ncert_downloader/books.py
ncert_downloader/cli.py
ncert_downloader/downloader.py
ncert_downloader/merger.py
ncert_downloader/models.py
ncert_downloader/utils.py
ncert_book_downloader-1.0.0.dist-info/METADATA
ncert_book_downloader-1.0.0.dist-info/WHEEL
ncert_book_downloader-1.0.0.dist-info/entry_points.txt
ncert_book_downloader-1.0.0.dist-info/top_level.txt
ncert_book_downloader-1.0.0.dist-info/RECORD
