Metadata-Version: 2.4
Name: ncert-book-downloader
Version: 1.0.0
Summary: Download all NCERT textbooks (Classes 1-12) in PDF format from the official NCERT website
Author: ncert-book-downloader contributors
Maintainer: ncert-book-downloader contributors
License: MIT
Project-URL: Homepage, https://github.com/dpandey/ncert-book-downloader
Project-URL: Documentation, https://github.com/dpandey/ncert-book-downloader#readme
Project-URL: Repository, https://github.com/dpandey/ncert-book-downloader
Project-URL: Issues, https://github.com/dpandey/ncert-book-downloader/issues
Project-URL: Changelog, https://github.com/dpandey/ncert-book-downloader/blob/main/CHANGELOG.md
Keywords: ncert,textbooks,education,india,cbse,pdf,downloader,books,study-material
Classifier: Development Status :: 5 - Production/Stable
Classifier: Environment :: Console
Classifier: Intended Audience :: Education
Classifier: Intended Audience :: End Users/Desktop
Classifier: License :: OSI Approved :: MIT License
Classifier: Operating System :: OS Independent
Classifier: Programming Language :: Python :: 3
Classifier: Programming Language :: Python :: 3.9
Classifier: Programming Language :: Python :: 3.10
Classifier: Programming Language :: Python :: 3.11
Classifier: Programming Language :: Python :: 3.12
Classifier: Programming Language :: Python :: 3.13
Classifier: Topic :: Education
Classifier: Topic :: Utilities
Requires-Python: >=3.9
License-File: LICENSE
Requires-Dist: requests>=2.28.0
Provides-Extra: merge
Requires-Dist: pypdf>=3.0.0; extra == "merge"
Provides-Extra: dev
Requires-Dist: pytest>=7.0.0; extra == "dev"
Requires-Dist: pytest-cov>=4.0.0; extra == "dev"
Requires-Dist: ruff>=0.1.0; extra == "dev"
Requires-Dist: mypy>=1.0.0; extra == "dev"
Requires-Dist: types-requests>=2.28.0; extra == "dev"
Dynamic: license-file
